codegnan/__init__.py
codegnan/quest_engine.py
codegnan/quiz.py
codegnan/resources/coding_questions.json
codegnan/resources/mcqs.json
codegnan-0.2.0.dist-info/licenses/LICENSE
codegnan-0.2.0.dist-info/METADATA
codegnan-0.2.0.dist-info/WHEEL
codegnan-0.2.0.dist-info/top_level.txt
codegnan-0.2.0.dist-info/RECORD
